{
  "ItemType": 8,
  "Id": 1155,
  "ShipId": 352,
  "DifficultyClass": 1,
  "Components": [
    {
      "ComponentId": 2022,
      "Locked": true,
      "X": 14,
      "Y": 6,
      "BarrelId": 1
    },
    {
      "ComponentId": 2022,
      "Locked": true,
      "X": 10,
      "Y": 6
    },
    {
      "ComponentId": 1023,
      "Locked": true,
      "X": 14,
      "Y": 9,
      "BarrelId": 3,
      "KeyBinding": 1
    },
    {
      "ComponentId": 1023,
      "Locked": true,
      "X": 18,
      "Y": 14,
      "BarrelId": 5,
      "KeyBinding": 1
    },
    {
      "ComponentId": 1023,
      "Locked": true,
      "X": 9,
      "Y": 9,
      "BarrelId": 2,
      "KeyBinding": 1
    },
    {
      "ComponentId": 1023,
      "Locked": true,
      "X": 5,
      "Y": 14,
      "BarrelId": 4,
      "KeyBinding": 1
    },
    {
      "ComponentId": 55,
      "Modification": 11,
      "Quality": 5,
      "Locked": true,
      "X": 16,
      "Y": 20,
      "BarrelId": -1,
      "KeyBinding": 2
    },
    {
      "ComponentId": 55,
      "Modification": 11,
      "Quality": 5,
      "Locked": true,
      "X": 18,
      "Y": 20,
      "BarrelId": -1,
      "KeyBinding": 2
    },
    {
      "ComponentId": 55,
      "Modification": 11,
      "Quality": 5,
      "Locked": true,
      "X": 6,
      "Y": 20,
      "BarrelId": -1,
      "KeyBinding": 2
    },
    {
      "ComponentId": 55,
      "Modification": 11,
      "Quality": 5,
      "Locked": true,
      "X": 8,
      "Y": 20,
      "BarrelId": -1,
      "KeyBinding": 2
    },
    {
      "ComponentId": 58,
      "Modification": 11,
      "Quality": 5,
      "Locked": true,
      "X": 16,
      "Y": 22,
      "BarrelId": -1,
      "KeyBinding": 2
    },
    {
      "ComponentId": 58,
      "Modification": 11,
      "Quality": 5,
      "Locked": true,
      "X": 18,
      "Y": 22,
      "BarrelId": -1,
      "KeyBinding": 2
    },
    {
      "ComponentId": 58,
      "Modification": 11,
      "Quality": 5,
      "Locked": true,
      "X": 6,
      "Y": 22,
      "BarrelId": -1,
      "KeyBinding": 2
    },
    {
      "ComponentId": 58,
      "Modification": 11,
      "Quality": 5,
      "Locked": true,
      "X": 8,
      "Y": 22,
      "BarrelId": -1,
      "KeyBinding": 2
    },
    {
      "ComponentId": 61,
      "Modification": 11,
      "Quality": 5,
      "Locked": true,
      "X": 11,
      "Y": 23,
      "BarrelId": -1,
      "KeyBinding": 2
    },
    {
      "ComponentId": 60,
      "Modification": 11,
      "Quality": 5,
      "Locked": true,
      "X": 14,
      "Y": 23,
      "BarrelId": -1,
      "KeyBinding": 2
    },
    {
      "ComponentId": 60,
      "Modification": 11,
      "Quality": 5,
      "Locked": true,
      "X": 14,
      "Y": 25,
      "BarrelId": -1,
      "KeyBinding": 2
    },
    {
      "ComponentId": 60,
      "Modification": 11,
      "Quality": 5,
      "Locked": true,
      "X": 14,
      "Y": 24,
      "BarrelId": -1,
      "KeyBinding": 2
    },
    {
      "ComponentId": 1005,
      "Modification": 12,
      "Quality": 5,
      "Locked": true,
      "X": 11,
      "Y": 19,
      "BarrelId": -1,
      "KeyBinding": 2
    },
    {
      "ComponentId": 1004,
      "Modification": 12,
      "Quality": 5,
      "Locked": true,
      "X": 11,
      "Y": 16,
      "BarrelId": -1,
      "KeyBinding": 2
    },
    {
      "ComponentId": 10,
      "Locked": true,
      "X": 16,
      "Y": 17,
      "BarrelId": -1,
      "KeyBinding": 2
    },
    {
      "ComponentId": 10,
      "Locked": true,
      "X": 7,
      "Y": 17,
      "BarrelId": -1,
      "KeyBinding": 2
    },
    {
      "ComponentId": 1007,
      "Locked": true,
      "X": 12,
      "Y": 1,
      "BarrelId": -1,
      "KeyBinding": 2
    },
    {
      "ComponentId": 1007,
      "Locked": true,
      "X": 12,
      "Y": 3,
      "BarrelId": -1,
      "KeyBinding": 2
    },
    {
      "ComponentId": 1007,
      "Locked": true,
      "X": 12,
      "Y": 5,
      "BarrelId": -1,
      "KeyBinding": 2
    },
    {
      "ComponentId": 1007,
      "Locked": true,
      "X": 12,
      "Y": 7,
      "BarrelId": -1,
      "KeyBinding": 2
    },
    {
      "ComponentId": 1007,
      "Locked": true,
      "X": 12,
      "Y": 9,
      "BarrelId": -1,
      "KeyBinding": 2
    },
    {
      "ComponentId": 1077,
      "Locked": true,
      "X": 10,
      "Y": 20,
      "BarrelId": -1,
      "KeyBinding": 2
    },
    {
      "ComponentId": 1077,
      "Locked": true,
      "X": 10,
      "Y": 21,
      "BarrelId": -1,
      "KeyBinding": 2
    },
    {
      "ComponentId": 1077,
      "Locked": true,
      "X": 10,
      "Y": 22,
      "BarrelId": -1,
      "KeyBinding": 2
    },
    {
      "ComponentId": 1077,
      "Locked": true,
      "X": 14,
      "Y": 16,
      "BarrelId": -1,
      "KeyBinding": 2
    },
    {
      "ComponentId": 1077,
      "Locked": true,
      "X": 14,
      "Y": 17,
      "BarrelId": -1,
      "KeyBinding": 2
    },
    {
      "ComponentId": 1077,
      "Locked": true,
      "X": 11,
      "Y": 19,
      "BarrelId": -1,
      "KeyBinding": 2
    },
    {
      "ComponentId": 11,
      "Locked": true,
      "X": 15,
      "Y": 14,
      "BarrelId": -1,
      "KeyBinding": 2
    },
    {
      "ComponentId": 11,
      "Locked": true,
      "X": 9,
      "Y": 14,
      "BarrelId": -1,
      "KeyBinding": 2
    },
    {
      "ComponentId": 71,
      "Locked": true,
      "X": 11,
      "Y": 14,
      "BarrelId": -1,
      "KeyBinding": 2
    },
    {
      "ComponentId": 71,
      "Locked": true,
      "X": 13,
      "Y": 14,
      "BarrelId": -1,
      "KeyBinding": 2
    },
    {
      "ComponentId": 71,
      "Locked": true,
      "X": 11,
      "Y": 12,
      "BarrelId": -1,
      "KeyBinding": 2
    },
    {
      "ComponentId": 71,
      "Locked": true,
      "X": 13,
      "Y": 12,
      "BarrelId": -1,
      "KeyBinding": 2
    }
  ]
}