{
  "ItemType": 8,
  "Id": 1070,
  "ShipId": 324,
  "Components": [
    {
      "ComponentId": 56,
      "Locked": true,
      "X": 8,
      "Y": 10,
      "BarrelId": -1
    },
    {
      "ComponentId": 56,
      "Locked": true,
      "X": 6,
      "Y": 10,
      "BarrelId": -1
    },
    {
      "ComponentId": 56,
      "Locked": true,
      "X": 6,
      "Y": 12,
      "BarrelId": -1
    },
    {
      "ComponentId": 56,
      "Locked": true,
      "X": 8,
      "Y": 12,
      "BarrelId": -1
    },
    {
      "ComponentId": 76,
      "Locked": true,
      "X": 6,
      "Y": 7,
      "BarrelId": -1
    },
    {
      "ComponentId": 76,
      "Locked": true,
      "X": 6,
      "Y": 4,
      "BarrelId": -1
    },
    {
      "ComponentId": 11,
      "Locked": true,
      "X": 9,
      "Y": 13,
      "BarrelId": -1
    },
    {
      "ComponentId": 11,
      "Locked": true,
      "X": 4,
      "Y": 13,
      "BarrelId": -1
    },
    {
      "ComponentId": 67,
      "Locked": true,
      "X": 5,
      "Y": 11,
      "BarrelId": -1
    },
    {
      "ComponentId": 67,
      "Locked": true,
      "X": 9,
      "Y": 11,
      "BarrelId": -1
    },
    {
      "ComponentId": 67,
      "Locked": true,
      "X": 9,
      "Y": 12,
      "BarrelId": -1
    },
    {
      "ComponentId": 67,
      "Locked": true,
      "X": 5,
      "Y": 12,
      "BarrelId": -1
    },
    {
      "ComponentId": 67,
      "Locked": true,
      "X": 6,
      "Y": 1,
      "BarrelId": -1
    },
    {
      "ComponentId": 67,
      "Locked": true,
      "X": 8,
      "Y": 1,
      "BarrelId": -1
    },
    {
      "ComponentId": 67,
      "Locked": true,
      "X": 6,
      "Y": 2,
      "BarrelId": -1
    },
    {
      "ComponentId": 67,
      "Locked": true,
      "X": 8,
      "Y": 2,
      "BarrelId": -1
    },
    {
      "ComponentId": 112,
      "Locked": true,
      "X": 6
    }
  ]
}