{
  "ItemType": 6,
  "Id": 3012,
  "Name": "Pursuer",
  "Faction": 208,
  "IconImage": "pursuer icon.png",
  "IconScale": 1.0,
  "ModelImage": "pursuer.png",
  "ModelScale": 0.7,
  "EngineColor": "#4C00FF",
  "Layout": "000004400000000004400000000002200000000002200000000012210000000012210000000012210000000112211000000112211000000112211000000112211000000055550000",
  "Barrels": [
    {
      "Position": {
        "x": 0.8
      },
      "PlatformType": 3,
      "WeaponClass": "CLTM"
    }
  ],
  "EnginePosition": {
    "x": -0.9
  },
  "EngineSize": 0.1,
  "ShipCategory": 6
}