{
  "ItemType": 8,
  "Id": 1254,
  "ShipId": 385,
  "DifficultyClass": 1,
  "Components": [
    {
      "ComponentId": 1140,
      "Locked": true,
      "X": 15,
      "Y": 21,
      "BarrelId": -1,
      "KeyBinding": 1
    },
    {
      "ComponentId": 1140,
      "Locked": true,
      "X": 10,
      "Y": 21,
      "BarrelId": -1,
      "KeyBinding": 1
    },
    {
      "ComponentId": 1141,
      "Locked": true,
      "X": 15,
      "Y": 23,
      "BarrelId": -1,
      "KeyBinding": 1
    },
    {
      "ComponentId": 1141,
      "Locked": true,
      "X": 10,
      "Y": 23,
      "BarrelId": -1,
      "KeyBinding": 1
    },
    {
      "ComponentId": 1150,
      "Locked": true,
      "X": 12,
      "Y": 22,
      "BarrelId": -1,
      "KeyBinding": 1
    },
    {
      "ComponentId": 1150,
      "Locked": true,
      "X": 12,
      "Y": 3,
      "BarrelId": -1,
      "KeyBinding": 1
    },
    {
      "ComponentId": 2100,
      "Locked": true,
      "X": 15,
      "Y": 17,
      "BarrelId": -1,
      "KeyBinding": 1
    },
    {
      "ComponentId": 1137,
      "Locked": true,
      "X": 14,
      "Y": 6,
      "BarrelId": -1,
      "KeyBinding": 1
    },
    {
      "ComponentId": 1137,
      "Locked": true,
      "X": 10,
      "Y": 6,
      "BarrelId": -1,
      "KeyBinding": 1
    },
    {
      "ComponentId": 1144,
      "Locked": true,
      "X": 15,
      "Y": 11,
      "BarrelId": -1,
      "KeyBinding": 1
    },
    {
      "ComponentId": 1144,
      "Locked": true,
      "X": 15,
      "Y": 9,
      "BarrelId": -1,
      "KeyBinding": 1
    },
    {
      "ComponentId": 1144,
      "Locked": true,
      "X": 10,
      "Y": 9,
      "BarrelId": -1,
      "KeyBinding": 1
    },
    {
      "ComponentId": 1144,
      "Locked": true,
      "X": 10,
      "Y": 11,
      "BarrelId": -1,
      "KeyBinding": 1
    },
    {
      "ComponentId": 1142,
      "Locked": true,
      "X": 19,
      "Y": 17,
      "BarrelId": -1,
      "KeyBinding": 1
    },
    {
      "ComponentId": 1142,
      "Locked": true,
      "X": 17,
      "Y": 7,
      "BarrelId": -1,
      "KeyBinding": 1
    },
    {
      "ComponentId": 1152,
      "Locked": true,
      "X": 12,
      "KeyBinding": 1
    },
    {
      "ComponentId": 1148,
      "Locked": true,
      "X": 16,
      "Y": 13,
      "BarrelId": 4
    },
    {
      "ComponentId": 1148,
      "Locked": true,
      "X": 8,
      "Y": 13,
      "BarrelId": 3
    },
    {
      "ComponentId": 1153,
      "Locked": true,
      "X": 15,
      "Y": 3,
      "BarrelId": 2,
      "KeyBinding": 2
    },
    {
      "ComponentId": 1153,
      "Locked": true,
      "X": 9,
      "Y": 3,
      "BarrelId": 1,
      "KeyBinding": 2
    },
    {
      "ComponentId": 2100,
      "Modification": 3,
      "Quality": 5,
      "Locked": true,
      "X": 8,
      "Y": 17,
      "BarrelId": -1,
      "KeyBinding": 3
    },
    {
      "ComponentId": 1142,
      "Modification": 3,
      "Quality": 5,
      "Locked": true,
      "X": 6,
      "Y": 17,
      "BarrelId": -1,
      "KeyBinding": 3
    },
    {
      "ComponentId": 1142,
      "Modification": 3,
      "Quality": 5,
      "Locked": true,
      "X": 8,
      "Y": 7,
      "BarrelId": -1,
      "KeyBinding": 3
    },
    {
      "ComponentId": 1140,
      "Locked": true,
      "X": 17,
      "Y": 21,
      "BarrelId": -1,
      "KeyBinding": 3
    },
    {
      "ComponentId": 1140,
      "Locked": true,
      "X": 8,
      "Y": 21,
      "BarrelId": -1,
      "KeyBinding": 3
    },
    {
      "ComponentId": 1141,
      "Locked": true,
      "X": 17,
      "Y": 23,
      "BarrelId": -1,
      "KeyBinding": 3
    },
    {
      "ComponentId": 1141,
      "Locked": true,
      "X": 8,
      "Y": 23,
      "BarrelId": -1,
      "KeyBinding": 3
    }
  ]
}